file_upload_sdk.py
large_file_upload_sdk-2.0.0.dist-info/LICENSE
large_file_upload_sdk-2.0.0.dist-info/METADATA
large_file_upload_sdk-2.0.0.dist-info/WHEEL
large_file_upload_sdk-2.0.0.dist-info/top_level.txt
large_file_upload_sdk-2.0.0.dist-info/RECORD
