Metadata-Version: 2.1
Name: large-file-upload-sdk
Version: 2.0.0
Summary: Large File Upload SDK - Support chunked upload, resumable transfer, and Token authentication
Home-page: https://github.com/your-username/file-upload-server
Author: SAIS Development Team
Author-email: SAIS Development Team <dev@sais.com.cn>
License: MIT
Project-URL: Homepage, https://github.com/your-username/file-upload-server
Project-URL: Documentation, https://github.com/your-username/file-upload-server#readme
Project-URL: Repository, https://github.com/your-username/file-upload-server
Project-URL: Bug Reports, https://github.com/your-username/file-upload-server/issues
Keywords: file upload,large file,chunked upload,resumable upload,file transfer,token authentication
Classifier: Development Status :: 5 - Production/Stable
Classifier: Intended Audience :: Developers
Classifier: Topic :: Internet :: WWW/HTTP :: HTTP Servers
Classifier: Topic :: Software Development :: Libraries :: Python Modules
Classifier: Topic :: System :: Archiving
Classifier: License :: OSI Approved :: MIT License
Classifier: Operating System :: OS Independent
Classifier: Programming Language :: Python :: 3
Classifier: Programming Language :: Python :: 3.7
Classifier: Programming Language :: Python :: 3.8
Classifier: Programming Language :: Python :: 3.9
Classifier: Programming Language :: Python :: 3.10
Classifier: Programming Language :: Python :: 3.11
Classifier: Programming Language :: Python :: 3.12
Requires-Python: >=3.7
License-File: LICENSE
Requires-Dist: requests >=2.25.0
Requires-Dist: urllib3 >=1.26.0
Provides-Extra: dev
Requires-Dist: pytest >=6.0 ; extra == 'dev'
Requires-Dist: pytest-cov >=2.0 ; extra == 'dev'
Requires-Dist: black >=21.0 ; extra == 'dev'
Requires-Dist: flake8 >=3.8 ; extra == 'dev'
